clustering/__init__.py
clustering/ddcal.py
ddcal-1.2.1.dist-info/licenses/LICENSE
ddcal-1.2.1.dist-info/METADATA
ddcal-1.2.1.dist-info/WHEEL
ddcal-1.2.1.dist-info/top_level.txt
ddcal-1.2.1.dist-info/RECORD
