Metadata-Version: 2.4
Name: ddcal
Version: 1.2.1
Summary: clustering packages with DDCAL algorithm
Author-email: Marian Lux <mlux.ddcal@swisdata.com>
License-Expression: MIT
Project-URL: Homepage, https://github.com/luxmar/DDCAL
Project-URL: Issues, https://github.com/luxmar/DDCAL/issues
Classifier: Programming Language :: Python :: 3
Classifier: Operating System :: OS Independent
Requires-Python: >=3.9
License-File: LICENSE
Requires-Dist: numpy>=1.21
Dynamic: license-file
